AUTHORS
COPYRIGHT
MANIFEST.in
setup.py
DIRECT/__init__.py
doc/Makefile
doc/make.bat
doc/make_doc_images.py
doc/images/six_hump.png
doc/source/conf.py
doc/source/index.rst
doc/source/install.rst
doc/source/reference.rst
doc/source/tutorial.rst
doc/source/sphinxext/apigen.py
doc/source/sphinxext/docscrape.py
doc/source/sphinxext/docscrape_sphinx.py
doc/source/sphinxext/inheritance_diagram.py
doc/source/sphinxext/ipython_console_highlighting.py
doc/source/sphinxext/numpydoc.py
src/DIRect.f
src/DIRmpi.f
src/DIRparallel.f
src/DIRpvm.f
src/DIRserial.f
src/DIRsubrout.f
src/direct-f2pywrappers.f
src/direct.pyf
src/directmodule.c
src/main.f
src/mainparallel.f
test/C6.py
test/SH.py
test/test_direct.py