Metadata-Version: 1.1
Name: DIRECT
Version: 1.0.1
Summary: Python wrapper to the DIRECT algorithm
Home-page: http://code.google.com/p/pydirect/
Author: Amit Aides
Author-email: amitibo@tx.technion.ac.il
License: MIT
Platform: any
Classifier: Development Status :: 5 - Production/Stable
Classifier: Programming Language :: Python
Classifier: License :: OSI Approved :: MIT License
Classifier: Intended Audience :: Science/Research
Classifier: Topic :: Scientific/Engineering
Classifier: Topic :: Scientific/Engineering :: Mathematics
Classifier: Operating System :: OS Independent
Requires: numpy
